soft/__init__.py
soft/extras.py
soft/soft.py
solar_ft-2.2.dist-info/licenses/LICENSE
solar_ft-2.2.dist-info/METADATA
solar_ft-2.2.dist-info/WHEEL
solar_ft-2.2.dist-info/top_level.txt
solar_ft-2.2.dist-info/RECORD
